gpxtable/__init__.py
gpxtable/cli.py
gpxtable/gpxtable.py
gpxtable/wsgi.py
gpxtable/static/android-chrome-192x192.png
gpxtable/static/android-chrome-512x512.png
gpxtable/static/apple-touch-icon.png
gpxtable/static/browserconfig.xml
gpxtable/static/favicon-16x16.png
gpxtable/static/favicon-32x32.png
gpxtable/static/favicon.ico
gpxtable/static/mstile-150x150.png
gpxtable/static/safari-pinned-tab.svg
gpxtable/static/site.webmanifest
gpxtable/templates/about.html
gpxtable/templates/base.html
gpxtable/templates/results.html
gpxtable/templates/upload.html
gpxtable-2.1.1.dist-info/licenses/LICENSE
gpxtable-2.1.1.dist-info/METADATA
gpxtable-2.1.1.dist-info/WHEEL
gpxtable-2.1.1.dist-info/entry_points.txt
gpxtable-2.1.1.dist-info/top_level.txt
gpxtable-2.1.1.dist-info/RECORD
