Metadata-Version: 2.4
Name: gpxtable
Version: 2.1.1
Summary: Generate tables of interesting GPX route and waypoint information
Author-email: Paul Traina <pleasantone@users.noreply.github.com>
Project-URL: Homepage, https://github.com/pleasantone/gpxtable
Project-URL: Issues, https://github.com/pleasantone/gpxtable/issues
Project-URL: Repository, https://github.com/pleasantone/gpxtable
Project-URL: Documentation, https://gpxtable.readthedocs.io
Keywords: GPS,GPX,Navigation,Track,Route,Waypoints
Classifier: Programming Language :: Python :: 3
Classifier: License :: OSI Approved :: GNU Affero General Public License v3 or later (AGPLv3+)
Classifier: Operating System :: OS Independent
Classifier: Development Status :: 5 - Production/Stable
Classifier: Framework :: Flask
Classifier: Environment :: Console
Requires-Python: >=3.9
License-File: LICENSE
Requires-Dist: astral>=3.2
Requires-Dist: gpxpy>=1.6.2
Requires-Dist: markdown2>=2.4.13
Requires-Dist: python-dateutil>=2.9
Provides-Extra: web
Requires-Dist: flask>=3.0.0; extra == "web"
Requires-Dist: requests>=2.32.3; extra == "web"
Requires-Dist: validators>=0.32; extra == "web"
Provides-Extra: gunicorn
Requires-Dist: flask>=3.0.0; extra == "gunicorn"
Requires-Dist: gunicorn>=22.0.0; extra == "gunicorn"
Requires-Dist: requests>=2.32.3; extra == "gunicorn"
Requires-Dist: validators>=0.32; extra == "gunicorn"
Provides-Extra: tests
Requires-Dist: pytest; extra == "tests"
Requires-Dist: pytest-flask; extra == "tests"
Requires-Dist: responses; extra == "tests"
Dynamic: license-file
